pyhpeimc/__init__.py
pyhpeimc/auth.py
pyhpeimc/objects.py
pyhpeimc/version.py
pyhpeimc/plat/__init__.py
pyhpeimc/plat/alarms.py
pyhpeimc/plat/device.py
pyhpeimc/plat/groups.py
pyhpeimc/plat/icc.py
pyhpeimc/plat/netassets.py
pyhpeimc/plat/operator.py
pyhpeimc/plat/perf.py
pyhpeimc/plat/system.py
pyhpeimc/plat/termaccess.py
pyhpeimc/plat/vlanm.py
pyhpeimc/plat/vrm.py
pyhpeimc/wsm/__init__.py
pyhpeimc/wsm/acinfo.py
pyhpeimc/wsm/apinfo.py
pyhpeimc/wsm/clientinfo.py
pyhpeimc-1.0.34.dist-info/DESCRIPTION.rst
pyhpeimc-1.0.34.dist-info/METADATA
pyhpeimc-1.0.34.dist-info/RECORD
pyhpeimc-1.0.34.dist-info/WHEEL
pyhpeimc-1.0.34.dist-info/entry_points.txt
pyhpeimc-1.0.34.dist-info/metadata.json
pyhpeimc-1.0.34.dist-info/top_level.txt
pyhpimc/__init__.py
pyhpimc/auth.py
pyhpimc/plat/__init__.py
pyhpimc/plat/alarms.py
pyhpimc/plat/device.py
pyhpimc/plat/groups.py
pyhpimc/plat/netassets.py
pyhpimc/plat/operator.py
pyhpimc/plat/termaccess.py
pyhpimc/plat/vlanm.py
