Metadata-Version: 2.0
Name: pyhpeimc
Version: 1.0.34
Summary: Python binding for HPE IMC REST API Interface
Home-page: https://github.com/HPENetworking/PYHPEIMC
Author: netmanchris
Author-email: chris_young@me.com
License: Apache2
Keywords: HPE IMC NMS RESTFUL API
Platform: UNKNOWN
Classifier: Development Status :: 4 - Beta
Classifier: Intended Audience :: Developers
Classifier: Intended Audience :: System Administrators
Classifier: License :: OSI Approved :: Apache Software License
Classifier: Programming Language :: Python
Classifier: Natural Language :: English
Classifier: Operating System :: OS Independent
Classifier: Topic :: Software Development :: Libraries :: Python Modules
Requires-Dist: requests
Provides-Extra: dev
Requires-Dist: check-manifest; extra == 'dev'
Provides-Extra: test
Requires-Dist: coverage; extra == 'test'
